[{"group_id": 88807, "name": "Matt Elmore", "cust_id": 88807, "display_name": "Matt Elmore", "lap_number": 0, "flags": 0, "incident": false, "session_time": 1276717, "session_start_time": null, "lap_time": -1, "team_fastest_lap": false, "personal_best_lap": false, "helmet": {"pattern": 3, "color1": "000000", "color2": "090e6c", "color3": "ffffff", "face_type": 0, "helmet_type": 0}, "license_level": 19, "car_number": "99", "lap_events": [], "ai": false, "car_contact": false, "contact": false, "pitted": false, "off_track": false, "lost_control": false, "invalid": false, "car_reset": false, "discontinuity": false, "tow": false, "black_flag": false}, {"group_id": 88807, "name": "Matt Elmore", "cust_id": 88807, "display_name": "Matt Elmore", "lap_number": 1, "flags": 8192, "incident": false, "session_time": 2275142, "session_start_time": null, "lap_time": 998425, "team_fastest_lap": false, "personal_best_lap": false, "helmet": {"pattern": 3, "color1": "000000", "color2": "090e6c", "color3": "ffffff", "face_type": 0, "helmet_type": 0}, "license_level": 19, "car_number": "99", "lap_events": [], "ai": false, "car_contact": false, "contact": false, "pitted": false, "off_track": false, "lost_control": false, "invalid": false, "car_reset": false, "discontinuity": false, "tow": false, "black_flag": false}, {"group_id": 88807, "name": "Matt Elmore", "cust_id": 88807, "display_name": "Matt Elmore", "lap_number": 2, "flags": 0, "incident": false, "session_time": 3193440, "session_start_time": null, "lap_time": 918298, "team_fastest_lap": false, "personal_best_lap": false, "helmet": {"pattern": 3, "color1": "000000", "color2": "090e6c", "color3": "ffffff", "face_type": 0, "helmet_type": 0}, "license_level": 19, "car_number": "99", "lap_events": [], "ai": false, "car_contact": false, "contact": false, "pitted": false, "off_track": false, "lost_control": false, "invalid": false, "car_reset": false, "discontinuity": false, "tow": false, "black_flag": false}, {"group_id": 88807, "name": "Matt Elmore", "cust_id": 88807, "display_name": "Matt Elmore", "lap_number": 3, "flags": 0, "incident": false, "session_time": 4101783, "session_start_time": null, "lap_time": 908343, "team_fastest_lap": false, "personal_best_lap": false, "helmet": {"pattern": 3, "color1": "000000", "color2": "090e6c", "color3": "ffffff", "face_type": 0, "helmet_type": 0}, "license_level": 19, "car_number": "99", "lap_events": [], "ai": false, "car_contact": false, "contact": false, "pitted": false, "off_track": false, "lost_control": false, "invalid": false, "car_reset": false, "discontinuity": false, "tow": false, "black_flag": false}, {"group_id": 88807, "name": "Matt Elmore", "cust_id": 88807, "display_name": "Matt Elmore", "lap_number": 4, "flags": 0, "incident": false, "session_time": 5010001, "session_start_time": null, "lap_time": 908218, "team_fastest_lap": false, "personal_best_lap": false, "helmet": {"pattern": 3, "color1": "000000", "color2": "090e6c", "color3": "ffffff", "face_type": 0, "helmet_type": 0}, "license_level": 19, "car_number": "99", "lap_events": [], "ai": false, "car_contact": false, "contact": false, "pitted": false, "off_track": false, "lost_control": false, "invalid": false, "car_reset": false, "discontinuity": false, "tow": false, "black_flag": false}, {"group_id": 88807, "name": "Matt Elmore", "cust_id": 88807, "display_name": "Matt Elmore", "lap_number": 5, "flags": 0, "incident": false, "session_time": 5915396, "session_start_time": null, "lap_time": 905395, "team_fastest_lap": false, "personal_best_lap": false, "helmet": {"pattern": 3, "color1": "000000", "color2": "090e6c", "color3": "ffffff", "face_type": 0, "helmet_type": 0}, "license_level": 19, "car_number": "99", "lap_events": [], "ai": false, "car_contact": false, "contact": false, "pitted": false, "off_track": false, "lost_control": false, "invalid": false, "car_reset": false, "discontinuity": false, "tow": false, "black_flag": false}, {"group_id": 88807, "name": "Matt Elmore", "cust_id": 88807, "display_name": "Matt Elmore", "lap_number": 6, "flags": 0, "incident": false, "session_time": 6824415, "session_start_time": null, "lap_time": 909019, "team_fastest_lap": false, "personal_best_lap": false, "helmet": {"pattern": 3, "color1": "000000", "color2": "090e6c", "color3": "ffffff", "face_type": 0, "helmet_type": 0}, "license_level": 19, "car_number": "99", "lap_events": [], "ai": false, "car_contact": false, "contact": false, "pitted": false, "off_track": false, "lost_control": false, "invalid": false, "car_reset": false, "discontinuity": false, "tow": false, "black_flag": false}, {"group_id": 88807, "name": "Matt Elmore", "cust_id": 88807, "display_name": "Matt Elmore", "lap_number": 7, "flags": 0, "incident": false, "session_time": 7730963, "session_start_time": null, "lap_time": 906548, "team_fastest_lap": false, "personal_best_lap": false, "helmet": {"pattern": 3, "color1": "000000", "color2": "090e6c", "color3": "ffffff", "face_type": 0, "helmet_type": 0}, "license_level": 19, "car_number": "99", "lap_events": [], "ai": false, "car_contact": false, "contact": false, "pitted": false, "off_track": false, "lost_control": false, "invalid": false, "car_reset": false, "discontinuity": false, "tow": false, "black_flag": false}, {"group_id": 88807, "name": "Matt Elmore", "cust_id": 88807, "display_name": "Matt Elmore", "lap_number": 8, "flags": 0, "incident": false, "session_time": 8640559, "session_start_time": null, "lap_time": 909596, "team_fastest_lap": false, "personal_best_lap": false, "helmet": {"pattern": 3, "color1": "000000", "color2": "090e6c", "color3": "ffffff", "face_type": 0, "helmet_type": 0}, "license_level": 19, "car_number": "99", "lap_events": [], "ai": false, "car_contact": false, "contact": false, "pitted": false, "off_track": false, "lost_control": false, "invalid": false, "car_reset": false, "discontinuity": false, "tow": false, "black_flag": false}, {"group_id": 88807, "name": "Matt Elmore", "cust_id": 88807, "display_name": "Matt Elmore", "lap_number": 9, "flags": 0, "incident": false, "session_time": 9546000, "session_start_time": null, "lap_time": 905441, "team_fastest_lap": false, "personal_best_lap": false, "helmet": {"pattern": 3, "color1": "000000", "color2": "090e6c", "color3": "ffffff", "face_type": 0, "helmet_type": 0}, "license_level": 19, "car_number": "99", "lap_events": [], "ai": false, "car_contact": false, "contact": false, "pitted": false, "off_track": false, "lost_control": false, "invalid": false, "car_reset": false, "discontinuity": false, "tow": false, "black_flag": false}, {"group_id": 88807, "name": "Matt Elmore", "cust_id": 88807, "display_name": "Matt Elmore", "lap_number": 10, "flags": 0, "incident": false, "session_time": 10452466, "session_start_time": null, "lap_time": 906466, "team_fastest_lap": false, "personal_best_lap": false, "helmet": {"pattern": 3, "color1": "000000", "color2": "090e6c", "color3": "ffffff", "face_type": 0, "helmet_type": 0}, "license_level": 19, "car_number": "99", "lap_events": [], "ai": false, "car_contact": false, "contact": false, "pitted": false, "off_track": false, "lost_control": false, "invalid": false, "car_reset": false, "discontinuity": false, "tow": false, "black_flag": false}, {"group_id": 88807, "name": "Matt Elmore", "cust_id": 88807, "display_name": "Matt Elmore", "lap_number": 11, "flags": 0, "incident": false, "session_time": 11358206, "session_start_time": null, "lap_time": 905740, "team_fastest_lap": false, "personal_best_lap": false, "helmet": {"pattern": 3, "color1": "000000", "color2": "090e6c", "color3": "ffffff", "face_type": 0, "helmet_type": 0}, "license_level": 19, "car_number": "99", "lap_events": [], "ai": false, "car_contact": false, "contact": false, "pitted": false, "off_track": false, "lost_control": false, "invalid": false, "car_reset": false, "discontinuity": false, "tow": false, "black_flag": false}, {"group_id": 88807, "name": "Matt Elmore", "cust_id": 88807, "display_name": "Matt Elmore", "lap_number": 12, "flags": 0, "incident": false, "session_time": 12263470, "session_start_time": null, "lap_time": 905264, "team_fastest_lap": true, "personal_best_lap": true, "helmet": {"pattern": 3, "color1": "000000", "color2": "090e6c", "color3": "ffffff", "face_type": 0, "helmet_type": 0}, "license_level": 19, "car_number": "99", "lap_events": [], "ai": false, "car_contact": false, "contact": false, "pitted": false, "off_track": false, "lost_control": false, "invalid": false, "car_reset": false, "discontinuity": false, "tow": false, "black_flag": false}, {"group_id": 88807, "name": "Matt Elmore", "cust_id": 88807, "display_name": "Matt Elmore", "lap_number": 13, "flags": 0, "incident": false, "session_time": 13173800, "session_start_time": null, "lap_time": 910330, "team_fastest_lap": false, "personal_best_lap": false, "helmet": {"pattern": 3, "color1": "000000", "color2": "090e6c", "color3": "ffffff", "face_type": 0, "helmet_type": 0}, "license_level": 19, "car_number": "99", "lap_events": [], "ai": false, "car_contact": false, "contact": false, "pitted": false, "off_track": false, "lost_control": false, "invalid": false, "car_reset": false, "discontinuity": false, "tow": false, "black_flag": false}, {"group_id": 88807, "name": "Matt Elmore", "cust_id": 88807, "display_name": "Matt Elmore", "lap_number": 14, "flags": 0, "incident": false, "session_time": 14081422, "session_start_time": null, "lap_time": 907622, "team_fastest_lap": false, "personal_best_lap": false, "helmet": {"pattern": 3, "color1": "000000", "color2": "090e6c", "color3": "ffffff", "face_type": 0, "helmet_type": 0}, "license_level": 19, "car_number": "99", "lap_events": [], "ai": false, "car_contact": false, "contact": false, "pitted": false, "off_track": false, "lost_control": false, "invalid": false, "car_reset": false, "discontinuity": false, "tow": false, "black_flag": false}, {"group_id": 88807, "name": "Matt Elmore", "cust_id": 88807, "display_name": "Matt Elmore", "lap_number": 15, "flags": 0, "incident": false, "session_time": 14990201, "session_start_time": null, "lap_time": 908779, "team_fastest_lap": false, "personal_best_lap": false, "helmet": {"pattern": 3, "color1": "000000", "color2": "090e6c", "color3": "ffffff", "face_type": 0, "helmet_type": 0}, "license_level": 19, "car_number": "99", "lap_events": [], "ai": false, "car_contact": false, "contact": false, "pitted": false, "off_track": false, "lost_control": false, "invalid": false, "car_reset": false, "discontinuity": false, "tow": false, "black_flag": false}, {"group_id": 88807, "name": "Matt Elmore", "cust_id": 88807, "display_name": "Matt Elmore", "lap_number": 16, "flags": 0, "incident": false, "session_time": 15896443, "session_start_time": null, "lap_time": 906242, "team_fastest_lap": false, "personal_best_lap": false, "helmet": {"pattern": 3, "color1": "000000", "color2": "090e6c", "color3": "ffffff", "face_type": 0, "helmet_type": 0}, "license_level": 19, "car_number": "99", "lap_events": [], "ai": false, "car_contact": false, "contact": false, "pitted": false, "off_track": false, "lost_control": false, "invalid": false, "car_reset": false, "discontinuity": false, "tow": false, "black_flag": false}, {"group_id": 88807, "name": "Matt Elmore", "cust_id": 88807, "display_name": "Matt Elmore", "lap_number": 17, "flags": 0, "incident": false, "session_time": 16803787, "session_start_time": null, "lap_time": 907344, "team_fastest_lap": false, "personal_best_lap": false, "helmet": {"pattern": 3, "color1": "000000", "color2": "090e6c", "color3": "ffffff", "face_type": 0, "helmet_type": 0}, "license_level": 19, "car_number": "99", "lap_events": [], "ai": false, "car_contact": false, "contact": false, "pitted": false, "off_track": false, "lost_control": false, "invalid": false, "car_reset": false, "discontinuity": false, "tow": false, "black_flag": false}, {"group_id": 88807, "name": "Matt Elmore", "cust_id": 88807, "display_name": "Matt Elmore", "lap_number": 18, "flags": 0, "incident": false, "session_time": 17710909, "session_start_time": null, "lap_time": 907122, "team_fastest_lap": false, "personal_best_lap": false, "helmet": {"pattern": 3, "color1": "000000", "color2": "090e6c", "color3": "ffffff", "face_type": 0, "helmet_type": 0}, "license_level": 19, "car_number": "99", "lap_events": [], "ai": false, "car_contact": false, "contact": false, "pitted": false, "off_track": false, "lost_control": false, "invalid": false, "car_reset": false, "discontinuity": false, "tow": false, "black_flag": false}, {"group_id": 88807, "name": "Matt Elmore", "cust_id": 88807, "display_name": "Matt Elmore", "lap_number": 19, "flags": 0, "incident": false, "session_time": 18618013, "session_start_time": null, "lap_time": 907104, "team_fastest_lap": false, "personal_best_lap": false, "helmet": {"pattern": 3, "color1": "000000", "color2": "090e6c", "color3": "ffffff", "face_type": 0, "helmet_type": 0}, "license_level": 19, "car_number": "99", "lap_events": [], "ai": false, "car_contact": false, "contact": false, "pitted": false, "off_track": false, "lost_control": false, "invalid": false, "car_reset": false, "discontinuity": false, "tow": false, "black_flag": false}, {"group_id": 88807, "name": "Matt Elmore", "cust_id": 88807, "display_name": "Matt Elmore", "lap_number": 20, "flags": 16384, "incident": false, "session_time": 19523586, "session_start_time": null, "lap_time": 905573, "team_fastest_lap": false, "personal_best_lap": false, "helmet": {"pattern": 3, "color1": "000000", "color2": "090e6c", "color3": "ffffff", "face_type": 0, "helmet_type": 0}, "license_level": 19, "car_number": "99", "lap_events": [], "ai": false, "car_contact": false, "contact": false, "pitted": false, "off_track": false, "lost_control": false, "invalid": false, "car_reset": false, "discontinuity": false, "tow": false, "black_flag": false}]